airflow_provider_bigquery_reservation/__init__.py
airflow_provider_bigquery_reservation/hooks/__init__.py
airflow_provider_bigquery_reservation/hooks/bigquery_reservation.py
airflow_provider_bigquery_reservation/operators/__init__.py
airflow_provider_bigquery_reservation/operators/bigquery_reservation.py
airflow_provider_bigquery_reservation-1.1.1.dist-info/LICENSE
airflow_provider_bigquery_reservation-1.1.1.dist-info/METADATA
airflow_provider_bigquery_reservation-1.1.1.dist-info/WHEEL
airflow_provider_bigquery_reservation-1.1.1.dist-info/entry_points.txt
airflow_provider_bigquery_reservation-1.1.1.dist-info/top_level.txt
airflow_provider_bigquery_reservation-1.1.1.dist-info/RECORD
